[
    {
        "caddress": "",
        "cdescription": null,
        "cname": "古祭壇及熱氣洞",
        "eaddress": "",
        "easting": 830325.0,
        "edescription": null,
        "ename": "Ancient Altars and Hot Pots",
        "faciType": null,
        "id": "606195",
        "nameStatus": "E",
        "northing": 831900.0,
        "score": 106886.890625,
        "type": "PL"
    },
    {
        "caddress": "",
        "cdescription": null,
        "cname": "嘉道理農場暨植物園古祭壇及熱氣洞",
        "eaddress": "",
        "easting": 830325.0,
        "edescription": null,
        "ename": "KADOORIE FARM AND BOTANIC GARDEN ANCIENT ALTARS AND HOT POTS",
        "faciType": null,
        "id": "53688",
        "nameStatus": "E",
        "northing": 831900.0,
        "score": 76485.5390625,
        "type": "PL"
    }
]