[
    {
        "caddress": "順隆街   33號",
        "cdescription": null,
        "cname": "順隆花園",
        "eaddress": "33 SHUN LUNG STREET  ",
        "easting": 841299.0,
        "edescription": null,
        "ename": "Greenside Paradise",
        "faciType": null,
        "id": "1107617534",
        "nameStatus": "E",
        "northing": 844940.0,
        "score": 46.31937026977539,
        "type": "B"
    },
    {
        "caddress": "香港海洋公園",
        "cdescription": null,
        "cname": "海洋金銀島",
        "eaddress": "Ocean Park Hong Kong",
        "easting": 835727.0,
        "edescription": null,
        "ename": "Ocean Paradise",
        "faciType": null,
        "id": "1103140300",
        "nameStatus": "E",
        "northing": 810503.0,
        "score": 46.31937026977539,
        "type": "B"
    },
    {
        "caddress": "杏花邨",
        "cdescription": null,
        "cname": "杏花新城",
        "eaddress": "HENG FA CHUEN",
        "easting": 842724.0,
        "edescription": null,
        "ename": "Paradise Mall",
        "faciType": null,
        "id": "1103128525",
        "nameStatus": "E",
        "northing": 815377.0,
        "score": 46.31937026977539,
        "type": "B"
    },
    {
        "caddress": "盛泰道   100號",
        "cdescription": null,
        "cname": "杏花新城",
        "eaddress": "100 SHING TAI ROAD  ",
        "easting": 842785.0,
        "edescription": null,
        "ename": "Paradise Mall",
        "faciType": null,
        "id": "1103129355",
        "nameStatus": "E",
        "northing": 815298.0,
        "score": 46.31937026977539,
        "type": "B"
    },
    {
        "caddress": "廣華街   3號",
        "cdescription": null,
        "cname": "百利達廣場",
        "eaddress": "3 KWONG WA STREET  ",
        "easting": 835843.0,
        "edescription": null,
        "ename": "Paradise Square",
        "faciType": null,
        "id": "1108236898",
        "nameStatus": "E",
        "northing": 819707.0,
        "score": 46.31937026977539,
        "type": "B"
    },
    {
        "caddress": "九龍尖沙咀彌敦道40號重慶大廈E座5字樓E2室",
        "cdescription": null,
        "cname": "PARADISE WORLD",
        "eaddress": "Flat E2, 5/F, Block E, Chungking Mansions,40 Nathan Road, Tsim Sha Tsui, Kowloon.",
        "easting": 835884.07860581,
        "edescription": null,
        "ename": "PARADISE WORLD",
        "faciType": "LLHG",
        "id": "99081135",
        "nameStatus": "E",
        "northing": 817476.92410359,
        "score": 46.31937026977539,
        "type": "F"
    },
    {
        "caddress": "香港海洋公園",
        "cdescription": null,
        "cname": "雀鳥劇場",
        "eaddress": "Ocean Park Hong Kong",
        "easting": 836252.0,
        "edescription": null,
        "ename": "Amazing Bird Show",
        "faciType": null,
        "id": "1810125662",
        "nameStatus": "E",
        "northing": 811772.0,
        "score": 44.712947845458984,
        "type": "B"
    },
    {
        "caddress": "新界元朗福德街56號精英大廈1字樓A座",
        "cdescription": null,
        "cname": "金雀會",
        "eaddress": "Flat A, 1/F, Jing Ying Building,56 Fook Tak Street,Yuen Long, New Territories",
        "easting": 820883.5,
        "edescription": null,
        "ename": "GOLDEN BIRD CLUB",
        "faciType": "CLUB",
        "id": "99083812",
        "nameStatus": "E",
        "northing": 834044.9,
        "score": 44.712947845458984,
        "type": "F"
    },
    {
        "caddress": "新界元朗福德街56號精英大廈1字樓B室",
        "cdescription": null,
        "cname": "金雀會",
        "eaddress": "Flat B, 1/F, Jing Ying Mansion, 56 Fook Tak Street, Yuen Long, New Territories",
        "easting": 820883.5,
        "edescription": null,
        "ename": "GOLDEN BIRD CLUB",
        "faciType": "CLUB",
        "id": "99083828",
        "nameStatus": "E",
        "northing": 834044.6,
        "score": 44.712947845458984,
        "type": "F"
    },
    {
        "caddress": "香港灣仔莊士敦道194-204號灣仔商業中心3字樓",
        "cdescription": null,
        "cname": "金雀會",
        "eaddress": "3/F, Wan Chai Commercial Centre,194-204 Johnston Road,Wan Chai, Hong Kong.",
        "easting": 836178.3,
        "edescription": null,
        "ename": "GOLDEN BIRD CLUB",
        "faciType": "CLUB",
        "id": "99084793",
        "nameStatus": "E",
        "northing": 815367.6,
        "score": 44.712947845458984,
        "type": "F"
    },
    {
        "caddress": "九龍旺角通菜街129-139號友誠大廈3-4字樓",
        "cdescription": null,
        "cname": "喜雀會",
        "eaddress": "3/F-4/F, Yau Shing Mansion, 129-139 Tung Choi Street, Mong Kok, Kowloon",
        "easting": 835568.0,
        "edescription": null,
        "ename": "LUCK BIRD CLUB",
        "faciType": "CLUB",
        "id": "99083668",
        "nameStatus": "E",
        "northing": 820194.0,
        "score": 44.712947845458984,
        "type": "F"
    },
    {
        "caddress": "雲咸街   22-28號",
        "cdescription": null,
        "cname": "四寶大樓",
        "eaddress": "22-28 WYNDHAM STREET  ",
        "easting": 834132.0,
        "edescription": null,
        "ename": "Sea Bird House",
        "faciType": null,
        "id": "1103126637",
        "nameStatus": "E",
        "northing": 815747.0,
        "score": 44.712947845458984,
        "type": "B"
    },
    {
        "caddress": "九龍油麻地彌敦道577&577A號高氏大樓3字樓A-B室",
        "cdescription": null,
        "cname": "CAT PARADISE LIMITED",
        "eaddress": "Flat A-B, 3/F, Ko's House, 577&577A Nathan Road, Yau Ma Tei, Kowloon",
        "easting": 835555.1,
        "edescription": null,
        "ename": "CAT PARADISE LIMITED",
        "faciType": "CLUB",
        "id": "99083538",
        "nameStatus": "E",
        "northing": 819580.4,
        "score": 41.9158821105957,
        "type": "F"
    },
    {
        "caddress": "九龍尖沙咀麼地道32-48號麗東大廈3字樓G室",
        "cdescription": null,
        "cname": "凱旋旅館(K11)",
        "eaddress": "Flat G, 3/F, Lyton Building, 32-48 Mody Road, Tsim Sha Tsui, Kowloon.",
        "easting": 836056.6,
        "edescription": null,
        "ename": "DREAM PARADISE INN",
        "faciType": "LLHG",
        "id": "990113972",
        "nameStatus": "E",
        "northing": 817580.2,
        "score": 41.9158821105957,
        "type": "F"
    },
    {
        "caddress": "九龍旺角彌敦道607號新興大廈2字樓201-204&211-212室",
        "cdescription": null,
        "cname": "銀雀聯誼會有限公司",
        "eaddress": "Flats 201-204 & 211-212, 2/F,Sun Hing Building, 607 Nathan Road,Mong Kok, Kowloon",
        "easting": 835519.9,
        "edescription": null,
        "ename": "S-BIRD CLUB LIMITED",
        "faciType": "CLUB",
        "id": "99083410",
        "nameStatus": "E",
        "northing": 819762.8,
        "score": 40.83122253417969,
        "type": "F"
    },
    {
        "caddress": "九龍旺角百利達廣場",
        "cdescription": null,
        "cname": "百利達購物廣場",
        "eaddress": "Paradise Square, Mong Kok, KLN",
        "easting": 835843.0,
        "edescription": null,
        "ename": "Paradise Shopping Square",
        "faciType": "MAL",
        "id": "552732",
        "nameStatus": "E",
        "northing": 819707.0,
        "score": 40.634212493896484,
        "type": "F"
    },
    {
        "caddress": "旺角廣華街3號",
        "cdescription": null,
        "cname": "百利達廣場",
        "eaddress": "3 Kwong Wa Street, Mong Kok",
        "easting": 835858.241,
        "edescription": null,
        "ename": "Paradise Square",
        "faciType": "CPO",
        "id": "544592",
        "nameStatus": "E",
        "northing": 819699.599,
        "score": 27.791624069213867,
        "type": "F"
    },
    {
        "caddress": "香港 東區 盛泰道100號",
        "cdescription": null,
        "cname": "杏花新城停車場",
        "eaddress": "100 SHING TAI ROAD, Eastern District, Hong Kong",
        "easting": 842660.0,
        "edescription": null,
        "ename": "Paradise Mall Carpark",
        "faciType": "CPO",
        "id": "533529",
        "nameStatus": "E",
        "northing": 815461.0,
        "score": 22.9661922454834,
        "type": "F"
    },
    {
        "caddress": "香港赤柱",
        "cdescription": null,
        "cname": "赤柱馬坑公園觀鳥角",
        "eaddress": "Stanley, HK",
        "easting": 839387.0,
        "edescription": null,
        "ename": "Stanley Ma Hang Park Bird Watching Corner",
        "faciType": "VPT",
        "id": "553020",
        "nameStatus": "E",
        "northing": 808860.0,
        "score": 19.4366397857666,
        "type": "F"
    },
    {
        "caddress": "香港杏花邨杏花新城西翼二樓217-230鋪",
        "cdescription": null,
        "cname": "Fusion-杏花新城, 杏花邨",
        "eaddress": "Shop No. 217-230, 2/F, West Commercial Block, Paradise Mall, Heng Fa Chuen, Hong Kong",
        "easting": 842724.0,
        "edescription": null,
        "ename": "Fusion-Paradise Mall, Heng Fa Chuen",
        "faciType": "SMK",
        "id": "549892",
        "nameStatus": "E",
        "northing": 815377.0,
        "score": 18.913557052612305,
        "type": "F"
    },
    {
        "caddress": "香港杏花新城1樓161號舖",
        "cdescription": null,
        "cname": "7-11便利店-杏花新城",
        "eaddress": "Shop Unit 161, Paradise Mall, Hang Fa Chuen, Hong Kong",
        "easting": 842737.0,
        "edescription": null,
        "ename": "7-Eleven Store-Paradise Mall",
        "faciType": "CVS",
        "id": "559628",
        "nameStatus": "E",
        "northing": 815382.0,
        "score": 16.964527130126953,
        "type": "F"
    },
    {
        "caddress": "香港杏花邨杏花新城地下G58A號舖",
        "cdescription": null,
        "cname": "7-11便利店-杏花新城",
        "eaddress": "Shop Unit G58A, G/F, Paradise Mall, Heng Fa Chuen, Hong Kong",
        "easting": 842795.379,
        "edescription": null,
        "ename": "7-Eleven Store-Paradise Mall",
        "faciType": "CVS",
        "id": "21095504",
        "nameStatus": "E",
        "northing": 815282.72,
        "score": 16.641376495361328,
        "type": "F"
    },
    {
        "caddress": "九龍旺角廣華街3號百利達購物廣場地下2號舖",
        "cdescription": null,
        "cname": "7-11便利店-百利達廣場",
        "eaddress": "Shop No. 2 on G/F, Paradise Square, No. 3 Kwong Wa Street, Mong Kok, Kowloon",
        "easting": 835864.0,
        "edescription": null,
        "ename": "7-Eleven Store-Paradise Square",
        "faciType": "CVS",
        "id": "531381",
        "nameStatus": "E",
        "northing": 819699.0,
        "score": 15.99773120880127,
        "type": "F"
    },
    {
        "caddress": "香港島柴灣盛泰道100號",
        "cdescription": null,
        "cname": "杏花新城 (西翼)充電站",
        "eaddress": "100 Sing Tai Road, Chai Wan",
        "easting": 842682.2812,
        "edescription": null,
        "ename": "Paradise Mall (West) Electric Vehicles Charging Point",
        "faciType": "3CP",
        "id": "CPEV00134",
        "nameStatus": "E",
        "northing": 815470.8208,
        "score": 12.147180557250977,
        "type": "F"
    },
    {
        "caddress": "九龍牛池灣宿舍及禮堂",
        "cdescription": null,
        "cname": "勝利道潮語浸信會讚頌之園",
        "eaddress": "Hostel and Hall, Ngau Chi Wan, KLN",
        "easting": 839503.0,
        "edescription": null,
        "ename": "Victory Avenue Swatow Baptist Church (Praising Paradise)",
        "faciType": "CHU",
        "id": "543328",
        "nameStatus": "E",
        "northing": 822336.0,
        "score": 12.147180557250977,
        "type": "F"
    },
    {
        "caddress": "SHOP NOS 11 & 12, G/F, EIGHTLAND GARDENS, 2, ON CHEE ROAD, TAI PO, NT",
        "cdescription": null,
        "cname": "漢城燕窩中西藥房",
        "eaddress": "SHOP NOS 11 & 12, G/F, EIGHTLAND GARDENS, 2, ON CHEE ROAD, TAI PO, NT",
        "easting": 835213.6,
        "edescription": null,
        "ename": "HON SHING BIRDS NEST DISPENSARY O/B HON SHING MEDICINE CO LTD.",
        "faciType": "RP",
        "id": "99075418",
        "nameStatus": "E",
        "northing": 834807.9,
        "score": 9.638529777526855,
        "type": "F"
    },
    {
        "caddress": "白沙灣盛泰道100號",
        "cdescription": null,
        "cname": "Wi-Fi.HK 熱點位置: 杏花新城",
        "eaddress": "100 Shing Tai Rd, Pak Sha Wan",
        "easting": 842774.6,
        "edescription": null,
        "ename": "Wi-Fi.HK Hotspot Locations: Paradise Mall",
        "faciType": "WIFIHK",
        "id": "990147644",
        "nameStatus": "E",
        "northing": 815319.0,
        "score": 3.2614262104034424,
        "type": "F"
    },
    {
        "caddress": "香港 香港仔黃竹坑",
        "cdescription": null,
        "cname": "Wi-Fi.HK 熱點位置: 海洋公園 - 雀鳥劇場",
        "eaddress": "Wong Chuk Hang, Aberdeen, Hong Kong",
        "easting": 836127.8,
        "edescription": null,
        "ename": "Wi-Fi.HK Hotspot Locations: Bird Theatre, Ocean Park",
        "faciType": "WIFIHK",
        "id": "990239812",
        "nameStatus": "E",
        "northing": 812018.3,
        "score": 3.030700445175171,
        "type": "F"
    },
    {
        "caddress": "香港 香港仔黃竹坑",
        "cdescription": null,
        "cname": "Wi-Fi.HK 熱點位置: 海洋公園 - 超速旋風",
        "eaddress": "Wong Chuk Hang, Aberdeen, Hong Kong",
        "easting": 836127.8,
        "edescription": null,
        "ename": "Wi-Fi.HK Hotspot Locations: Whirly Bird Ride, Ocean Park",
        "faciType": "WIFIHK",
        "id": "990239858",
        "nameStatus": "E",
        "northing": 812018.3,
        "score": 2.8472354412078857,
        "type": "F"
    },
    {
        "caddress": "杏花新城",
        "cdescription": null,
        "cname": "回收機構及收集點： 港鐵公司",
        "eaddress": "Paradise Mall",
        "easting": 842785.0,
        "edescription": null,
        "ename": "Recycling Organisations and Collection Points: MTRC",
        "faciType": "DO_NGO",
        "id": "99090785",
        "nameStatus": "E",
        "northing": 815298.0,
        "score": 2.318850040435791,
        "type": "F"
    },
    {
        "caddress": "灣仔駱克道414-430號地下及1-2層1A號舖New Paradise Health Club",
        "cdescription": null,
        "cname": "已登記的WiFi 熱點: Hong Kong Telecommunications (HKT) Limited (APID 05714)",
        "eaddress": "Unit Shop 1A, GF, 1-2F/F, Block New Paradise Health Club, 414-430 Lockhart Rd, Wan Chai",
        "easting": 836646.7,
        "edescription": null,
        "ename": "Registered WiFi Access Points: Hong Kong Telecommunications (HKT) Limited (APID 05714)",
        "faciType": "WIFI",
        "id": "990263744",
        "nameStatus": "E",
        "northing": 815629.6,
        "score": 1.0946540832519531,
        "type": "F"
    },
    {
        "caddress": "香港柴灣盛泰道100號杏花邨杏花新城地下G46鋪",
        "cdescription": null,
        "cname": "回收機構及收集點： 麥當勞",
        "eaddress": "Shop Unit G46, G/F, Paradise Mall, Heng Fa Chuen, 100 Shing Tai Road, Chai Wan, HK",
        "easting": 842785.0,
        "edescription": null,
        "ename": "Recycling Organisations and Collection Points: McDonald's",
        "faciType": "DO_NGO",
        "id": "990105240",
        "nameStatus": "E",
        "northing": 815298.0,
        "score": 0.9552093744277954,
        "type": "F"
    },
    {
        "caddress": "柴灣盛泰道100號杏花邨杏花新城地下G46號店",
        "cdescription": null,
        "cname": "已登記的WiFi 熱點: 香港寬頻網絡有限公司 (APID 04142)",
        "eaddress": "Unit G46, G/F, Paradise Mall, 100 Shing Tai Road",
        "easting": 842785.0,
        "edescription": null,
        "ename": "Registered WiFi Access Points: Hong Kong Broadband Network Limited (APID 04142)",
        "faciType": "WIFI",
        "id": "990260604",
        "nameStatus": "E",
        "northing": 815298.0,
        "score": 0.719303548336029,
        "type": "F"
    },
    {
        "caddress": "柴灣盛泰道100號杏花邨杏花新城地下G46號店",
        "cdescription": null,
        "cname": "已登記的WiFi 熱點: Y5ZONE Limited (APID 08669)",
        "eaddress": "G46, G/F, Paradise Mall, 100 Shing Tai Road",
        "easting": 842785.0,
        "edescription": null,
        "ename": "Registered WiFi Access Points: Y5ZONE Limited (APID 08669)",
        "faciType": "WIFI",
        "id": "990269682",
        "nameStatus": "E",
        "northing": 815298.0,
        "score": 0.6765060424804688,
        "type": "F"
    },
    {
        "caddress": "柴灣盛泰道100號杏花邨杏花新城地下41A號店",
        "cdescription": null,
        "cname": "已登記的WiFi 熱點: 香港寬頻網絡有限公司 (APID 04141)",
        "eaddress": "Unit 41A, G/F, Heng Fa Paradise Mall, 100 Shing Tai Road",
        "easting": 842785.0,
        "edescription": null,
        "ename": "Registered WiFi Access Points: Hong Kong Broadband Network Limited (APID 04141)",
        "faciType": "WIFI",
        "id": "990260602",
        "nameStatus": "E",
        "northing": 815298.0,
        "score": 0.6385160088539124,
        "type": "F"
    },
    {
        "caddress": "柴灣盛泰道100號杏花邨杏花新城161號",
        "cdescription": null,
        "cname": "已登記的WiFi 熱點: Hong Kong Telecommunications (HKT) Limited (APID 06445)",
        "eaddress": "Unit Shop 161, Paradise Mall, Hang Fa Chuen, Chai Wan",
        "easting": 842785.0,
        "edescription": null,
        "ename": "Registered WiFi Access Points: Hong Kong Telecommunications (HKT) Limited (APID 06445)",
        "faciType": "WIFI",
        "id": "990265236",
        "nameStatus": "E",
        "northing": 815298.0,
        "score": 0.6385160088539124,
        "type": "F"
    },
    {
        "caddress": "柴灣盛泰道100號杏花邨杏花新城地下G58A號店",
        "cdescription": null,
        "cname": "已登記的WiFi 熱點: Hong Kong Telecommunications (HKT) Limited (APID 06446)",
        "eaddress": "Unit Shop G58A, G/F, Paradise Mall, Heng Fa Chuen",
        "easting": 842785.0,
        "edescription": null,
        "ename": "Registered WiFi Access Points: Hong Kong Telecommunications (HKT) Limited (APID 06446)",
        "faciType": "WIFI",
        "id": "990265238",
        "nameStatus": "E",
        "northing": 815298.0,
        "score": 0.6385160088539124,
        "type": "F"
    },
    {
        "caddress": "柴灣盛泰道100號杏花邨杏花新城G38號店",
        "cdescription": null,
        "cname": "已登記的WiFi 熱點: Hong Kong Telecommunications (HKT) Limited (APID 06447)",
        "eaddress": "Unit Shop G38, Paradise Mall, Heng Fa Chuen, Chai Wan",
        "easting": 842785.0,
        "edescription": null,
        "ename": "Registered WiFi Access Points: Hong Kong Telecommunications (HKT) Limited (APID 06447)",
        "faciType": "WIFI",
        "id": "990265240",
        "nameStatus": "E",
        "northing": 815298.0,
        "score": 0.6385160088539124,
        "type": "F"
    },
    {
        "caddress": "油麻地廣華街3號百利達廣場",
        "cdescription": null,
        "cname": "已登記的WiFi 熱點: Hong Kong Telecommunications (HKT) Limited (APID 05559)",
        "eaddress": "Unit Shop 2, G/F, Paradise Square, 3 Kwong Wa St",
        "easting": 835843.0,
        "edescription": null,
        "ename": "Registered WiFi Access Points: Hong Kong Telecommunications (HKT) Limited (APID 05559)",
        "faciType": "WIFI",
        "id": "990263434",
        "nameStatus": "E",
        "northing": 819707.0,
        "score": 0.6045665144920349,
        "type": "F"
    },
    {
        "caddress": "柴灣盛泰道100號杏花邨杏花新城G51-52號店",
        "cdescription": null,
        "cname": "已登記的WiFi 熱點: Hong Kong Telecommunications (HKT) Limited (APID 06444)",
        "eaddress": "Unit G51-52, Paradise Mall, Heng Fa Chuen, 100 Shing Tai Rd",
        "easting": 842785.0,
        "edescription": null,
        "ename": "Registered WiFi Access Points: Hong Kong Telecommunications (HKT) Limited (APID 06444)",
        "faciType": "WIFI",
        "id": "990265234",
        "nameStatus": "E",
        "northing": 815298.0,
        "score": 0.5740454792976379,
        "type": "F"
    },
    {
        "caddress": "灣仔駱克道339-347號地下至2層新瀛閣桑拿",
        "cdescription": null,
        "cname": "已登記的WiFi 熱點: Hong Kong Telecommunications (HKT) Limited (APID 05690)",
        "eaddress": "GF-2F/F, Block Sunny Paradise Sauna, 339-347 Lockhart Rd, Wan Chai",
        "easting": 836450.9,
        "edescription": null,
        "ename": "Registered WiFi Access Points: Hong Kong Telecommunications (HKT) Limited (APID 05690)",
        "faciType": "WIFI",
        "id": "990263696",
        "nameStatus": "E",
        "northing": 815605.0,
        "score": 0.5464585423469543,
        "type": "F"
    },
    {
        "caddress": "柴灣盛泰道100號杏花邨杏花新城地下GL28號店",
        "cdescription": null,
        "cname": "已登記的WiFi 熱點: Hong Kong Telecommunications (HKT) Limited (APID 06457)",
        "eaddress": "Unit Shop GL 28, 1/F, Paradise Mall, 100 Shing Tai Road Heng Fa Chuen Chai Wan",
        "easting": 842785.0,
        "edescription": null,
        "ename": "Registered WiFi Access Points: Hong Kong Telecommunications (HKT) Limited (APID 06457)",
        "faciType": "WIFI",
        "id": "990265260",
        "nameStatus": "E",
        "northing": 815298.0,
        "score": 0.4985430836677551,
        "type": "F"
    },
    {
        "caddress": "柴灣盛泰道100號杏花邨杏花新城地下GL31號店",
        "cdescription": null,
        "cname": "已登記的WiFi 熱點: Hong Kong Telecommunications (HKT) Limited (APID 06458)",
        "eaddress": "Unit Shop GL 31, 1/F, Paradise Mall, 100 Shing Tai Road, Heng Fa Chuen Chai Wan",
        "easting": 842785.0,
        "edescription": null,
        "ename": "Registered WiFi Access Points: Hong Kong Telecommunications (HKT) Limited (APID 06458)",
        "faciType": "WIFI",
        "id": "990265262",
        "nameStatus": "E",
        "northing": 815298.0,
        "score": 0.4985430836677551,
        "type": "F"
    },
    {
        "caddress": "柴灣盛泰道100號杏花邨杏花新城地下GL33號店",
        "cdescription": null,
        "cname": "已登記的WiFi 熱點: Hong Kong Telecommunications (HKT) Limited (APID 06459)",
        "eaddress": "Unit Shop GL 33, 1/F, Paradise Mall, 100 Shing Tai Road, Heng Fa Chuen CHai Wan",
        "easting": 842785.0,
        "edescription": null,
        "ename": "Registered WiFi Access Points: Hong Kong Telecommunications (HKT) Limited (APID 06459)",
        "faciType": "WIFI",
        "id": "990265264",
        "nameStatus": "E",
        "northing": 815298.0,
        "score": 0.4985430836677551,
        "type": "F"
    },
    {
        "caddress": "柴灣盛泰道100號杏花邨杏花新城地下GL36號店",
        "cdescription": null,
        "cname": "已登記的WiFi 熱點: Hong Kong Telecommunications (HKT) Limited (APID 06460)",
        "eaddress": "Unit Shop GL 36, 1/F, Paradise Mall, 100 Shing Tai Road, Heng Fa Chuen Chai Wan",
        "easting": 842785.0,
        "edescription": null,
        "ename": "Registered WiFi Access Points: Hong Kong Telecommunications (HKT) Limited (APID 06460)",
        "faciType": "WIFI",
        "id": "990265266",
        "nameStatus": "E",
        "northing": 815298.0,
        "score": 0.4985430836677551,
        "type": "F"
    },
    {
        "caddress": "柴灣盛泰道100號杏花邨杏花新城地下GL42號店",
        "cdescription": null,
        "cname": "已登記的WiFi 熱點: Hong Kong Telecommunications (HKT) Limited (APID 06461)",
        "eaddress": "Unit Shop GL 42, 1/F, Paradise Mall, 100 Shing Tai Road, Heng Fa Chuen Chai Wan",
        "easting": 842785.0,
        "edescription": null,
        "ename": "Registered WiFi Access Points: Hong Kong Telecommunications (HKT) Limited (APID 06461)",
        "faciType": "WIFI",
        "id": "990265268",
        "nameStatus": "E",
        "northing": 815298.0,
        "score": 0.4985430836677551,
        "type": "F"
    },
    {
        "caddress": "柴灣盛泰道100號杏花邨杏花新城地下GL45號店",
        "cdescription": null,
        "cname": "已登記的WiFi 熱點: Hong Kong Telecommunications (HKT) Limited (APID 06462)",
        "eaddress": "Unit Shop GL 45, 1/F, Paradise Mall, 100 Shing Tai Road, Heng Fa Chuen Chai Wan",
        "easting": 842785.0,
        "edescription": null,
        "ename": "Registered WiFi Access Points: Hong Kong Telecommunications (HKT) Limited (APID 06462)",
        "faciType": "WIFI",
        "id": "990265270",
        "nameStatus": "E",
        "northing": 815298.0,
        "score": 0.4985430836677551,
        "type": "F"
    },
    {
        "caddress": "柴灣盛泰道100號杏花邨杏花新城地下GL47號店",
        "cdescription": null,
        "cname": "已登記的WiFi 熱點: Hong Kong Telecommunications (HKT) Limited (APID 06463)",
        "eaddress": "Unit Shop GL 47, 1/F, Paradise Mall, 100 Shing Tai Road, Heng Fa Chuen Chai Wan",
        "easting": 842785.0,
        "edescription": null,
        "ename": "Registered WiFi Access Points: Hong Kong Telecommunications (HKT) Limited (APID 06463)",
        "faciType": "WIFI",
        "id": "990265272",
        "nameStatus": "E",
        "northing": 815298.0,
        "score": 0.4985430836677551,
        "type": "F"
    },
    {
        "caddress": "柴灣盛泰道100號杏花邨杏花新城地下GL51號店",
        "cdescription": null,
        "cname": "已登記的WiFi 熱點: Hong Kong Telecommunications (HKT) Limited (APID 06464)",
        "eaddress": "Unit Shop GL 51, 1/F, Paradise Mall, 100 Shing Tai Road, Heng Fa Chuen Chai Wan",
        "easting": 842785.0,
        "edescription": null,
        "ename": "Registered WiFi Access Points: Hong Kong Telecommunications (HKT) Limited (APID 06464)",
        "faciType": "WIFI",
        "id": "990265274",
        "nameStatus": "E",
        "northing": 815298.0,
        "score": 0.4985430836677551,
        "type": "F"
    },
    {
        "caddress": "柴灣盛泰道100號杏花邨杏花新城地下GL53號店",
        "cdescription": null,
        "cname": "已登記的WiFi 熱點: Hong Kong Telecommunications (HKT) Limited (APID 06465)",
        "eaddress": "Unit Shop GL 53, 1/F, Paradise Mall, 100 Shing Tai Road, Heng Fa Chuen Chai Wan",
        "easting": 842785.0,
        "edescription": null,
        "ename": "Registered WiFi Access Points: Hong Kong Telecommunications (HKT) Limited (APID 06465)",
        "faciType": "WIFI",
        "id": "990265276",
        "nameStatus": "E",
        "northing": 815298.0,
        "score": 0.4985430836677551,
        "type": "F"
    }
]